{
  "info": {
    "_postman_id": "10ae71ab-7389-4edb-8dd0-ea7cc48e6d61",
    "name": "ProyectoFinalCamaras Copy",
    "schema": "https://schema.getpostman.com/json/collection/v2.1.0/collection.json",
    "_exporter_id": "48332520",
    "_collection_link": "https://go.postman.co/collection/48332520-10ae71ab-7389-4edb-8dd0-ea7cc48e6d61?source=collection_link"
  },
  "item": [
    {
      "name": "Autentificación",
      "item": [
        {
          "name": "Register",
          "request": {
            "method": "POST",
            "header": [],
            "body": {
              "mode": "formdata",
              "formdata": [
                {
                  "key": "name",
                  "value": "Joab",
                  "type": "text",
                  "uuid": "abd4919a-12c1-42f8-9b5a-58e08777b1e6"
                },
                {
                  "key": "surname",
                  "value": "Selvi",
                  "type": "text",
                  "uuid": "77403613-e2e1-47a3-8744-71a40b0581f5"
                },
                {
                  "key": "username",
                  "value": "Joab_Selvi",
                  "type": "text",
                  "uuid": "2d80689a-f74c-4508-9e34-5cb449cfe378"
                },
                {
                  "key": "email",
                  "value": "jregil0re@gmail.com",
                  "type": "text",
                  "uuid": "9a49a1de-8480-43e7-9d0a-ce07a305e2df"
                },
                {
                  "key": "password",
                  "value": "Lolita151223",
                  "type": "text",
                  "uuid": "1642bca5-d0fc-44f2-94c6-98e955eab3ac"
                },
                {
                  "key": "phone",
                  "value": "42653798",
                  "type": "text",
                  "uuid": "d979400e-608e-421b-9e77-2418390d384b"
                },
                {
                  "key": "placa",
                  "value": "P-123ABC",
                  "type": "text",
                  "uuid": "d0236ad3-cfef-48ee-8d93-ad6bace3fae2"
                },
                {
                  "key": "profilePicture",
                  "type": "file",
                  "uuid": "1b06eab3-532c-409a-a743-959b7a2574f1",
                  "src": "/C:/Users/estua/Downloads/moni.jpg"
                }
              ]
            },
            "url": {
              "raw": "http://localhost:3005/api/v1/auth/register",
              "protocol": "http",
              "host": [
                "localhost"
              ],
              "port": "3005",
              "path": [
                "api",
                "v1",
                "auth",
                "register"
              ]
            }
          },
          "response": []
        },
        {
          "name": "resend-verification",
          "request": {
            "method": "POST",
            "header": [],
            "body": {
              "mode": "raw",
              "raw": "{\r\n  \"email\": \"alejandroarochavirula@gmail.com\"\r\n}\r\n",
              "options": {
                "raw": {
                  "language": "json"
                }
              }
            },
            "url": {
              "raw": "http://localhost:3005/api/v1/auth/resend-verification",
              "protocol": "http",
              "host": [
                "localhost"
              ],
              "port": "3005",
              "path": [
                "api",
                "v1",
                "auth",
                "resend-verification"
              ]
            }
          },
          "response": []
        },
        {
          "name": "verify-email",
          "request": {
            "method": "POST",
            "header": [],
            "body": {
              "mode": "raw",
              "raw": "{\r\n  \"token\": \"uwrYTtXsXfhLKs4R9X8UfDYFukNWE-SJ-5lQO3f4MrY\"\r\n}\r\n",
              "options": {
                "raw": {
                  "language": "json"
                }
              }
            },
            "url": {
              "raw": "http://localhost:3005/api/v1/auth/verify-email",
              "protocol": "http",
              "host": [
                "localhost"
              ],
              "port": "3005",
              "path": [
                "api",
                "v1",
                "auth",
                "verify-email"
              ]
            }
          },
          "response": []
        },
        {
          "name": "Login",
          "request": {
            "method": "POST",
            "header": [],
            "body": {
              "mode": "raw",
              "raw": "{\r\n  \"emailOrUsername\": \"jregil0re@gmail.com\",\r\n  \"password\": \"Lolita151223\"\r\n}\r\n",
              "options": {
                "raw": {
                  "language": "json"
                }
              }
            },
            "url": {
              "raw": "http://localhost:3005/api/v1/auth/login",
              "protocol": "http",
              "host": [
                "localhost"
              ],
              "port": "3005",
              "path": [
                "api",
                "v1",
                "auth",
                "login"
              ]
            }
          },
          "response": []
        },
        {
          "name": "forgot-password",
          "request": {
            "method": "POST",
            "header": [],
            "body": {
              "mode": "raw",
              "raw": "{\r\n  \"email\": \"alejandroarochavirula@gmail.com\"\r\n}\r\n",
              "options": {
                "raw": {
                  "language": "json"
                }
              }
            },
            "url": {
              "raw": "http://localhost:3005/api/v1/auth/forgot-password",
              "protocol": "http",
              "host": [
                "localhost"
              ],
              "port": "3005",
              "path": [
                "api",
                "v1",
                "auth",
                "forgot-password"
              ]
            }
          },
          "response": []
        },
        {
          "name": "reset-password",
          "request": {
            "method": "POST",
            "header": [],
            "body": {
              "mode": "raw",
              "raw": "{\r\n  \"token\": \"TOKEN_DEL_CORREO\",\r\n  \"newPassword\": \"NuevaPassword123\"\r\n}\r\n",
              "options": {
                "raw": {
                  "language": "json"
                }
              }
            },
            "url": {
              "raw": "http://localhost:3005/api/v1/auth/reset-password",
              "protocol": "http",
              "host": [
                "localhost"
              ],
              "port": "3005",
              "path": [
                "api",
                "v1",
                "auth",
                "reset-password"
              ]
            }
          },
          "response": []
        },
        {
          "name": "users-list",
          "request": {
            "auth": {
              "type": "bearer",
              "bearer": [
                {
                  "key": "token",
                  "value": "{{vault:authorization-secret}}",
                  "type": "string"
                }
              ]
            },
            "method": "GET",
            "header": [],
            "url": {
              "raw": "http://localhost:3005/api/v1/admin/roles/users",
              "protocol": "http",
              "host": [
                "localhost"
              ],
              "port": "3005",
              "path": [
                "api",
                "v1",
                "admin",
                "roles",
                "users"
              ]
            }
          },
          "response": []
        },
        {
          "name": "Asignar Rol Admin/User",
          "request": {
            "auth": {
              "type": "bearer",
              "bearer": [
                {
                  "key": "token",
                  "value": "{{vault:authorization-secret}}",
                  "type": "string"
                }
              ]
            },
            "method": "POST",
            "header": [],
            "body": {
              "mode": "raw",
              "raw": "{\r\n  \"userId\": \"usr_jg2mMrnYDmyZ\",\r\n  \"roleName\": \"USER_ROLE\"\r\n}\r\n",
              "options": {
                "raw": {
                  "language": "json"
                }
              }
            },
            "url": {
              "raw": "http://localhost:3005/api/v1/admin/roles/assign",
              "protocol": "http",
              "host": [
                "localhost"
              ],
              "port": "3005",
              "path": [
                "api",
                "v1",
                "admin",
                "roles",
                "assign"
              ]
            }
          },
          "response": []
        },
        {
          "name": "Cambiar de rol usuario/admin",
          "request": {
            "auth": {
              "type": "bearer",
              "bearer": [
                {
                  "key": "token",
                  "value": "{{vault:authorization-secret}}",
                  "type": "string"
                }
              ]
            },
            "method": "DELETE",
            "header": [],
            "body": {
              "mode": "raw",
              "raw": "{\r\n  \"userId\": \"usr_jg2mMrnYDmyZ\",\r\n  \"roleName\": \"ADMIN_ROLE\"\r\n}",
              "options": {
                "raw": {
                  "language": "json"
                }
              }
            },
            "url": {
              "raw": "http://localhost:3005/api/v1/admin/roles/remove",
              "protocol": "http",
              "host": [
                "localhost"
              ],
              "port": "3005",
              "path": [
                "api",
                "v1",
                "admin",
                "roles",
                "remove"
              ]
            }
          },
          "response": []
        }
      ]
    },
    {
      "name": "Entidades",
      "item": [
        {
          "name": "Menu usuarios",
          "item": [
            {
              "name": "tarjeta de credito",
              "item": [
                {
                  "name": "Agregar TarjetaCredito",
                  "request": {
                    "auth": {
                      "type": "bearer",
                      "bearer": [
                        {
                          "key": "token",
                          "value": "{{vault:authorization-secret}}",
                          "type": "string"
                        }
                      ]
                    },
                    "method": "POST",
                    "header": [],
                    "body": {
                      "mode": "raw",
                      "raw": "{\r\n  \"numeroTarjeta\":    \"5500 0000 0000 0004\",\r\n  \"fechaVencimiento\": \"12/29\",\r\n  \"cvv\":              \"123\",\r\n  \"nombreTitular\":    \"joab regil\",\r\n  \"tipoTarjeta\":      \"CREDITO\",\r\n  \"alias\":            \"Mi Visa\"\r\n}",
                      "options": {
                        "raw": {
                          "language": "json"
                        }
                      }
                    },
                    "url": {
                      "raw": "http://localhost:3005/api/v1/saldo/agregar-tarjeta",
                      "protocol": "http",
                      "host": [
                        "localhost"
                      ],
                      "port": "3005",
                      "path": [
                        "api",
                        "v1",
                        "saldo",
                        "agregar-tarjeta"
                      ]
                    }
                  },
                  "response": []
                },
                {
                  "name": "Ver TarjetaCredito User",
                  "protocolProfileBehavior": {
                    "disableBodyPruning": true
                  },
                  "request": {
                    "auth": {
                      "type": "bearer",
                      "bearer": [
                        {
                          "key": "token",
                          "value": "{{vault:authorization-secret}}",
                          "type": "string"
                        }
                      ]
                    },
                    "method": "GET",
                    "header": [],
                    "body": {
                      "mode": "raw",
                      "raw": "",
                      "options": {
                        "raw": {
                          "language": "json"
                        }
                      }
                    },
                    "url": {
                      "raw": "http://localhost:3005/api/v1/saldo/mis-tarjetas",
                      "protocol": "http",
                      "host": [
                        "localhost"
                      ],
                      "port": "3005",
                      "path": [
                        "api",
                        "v1",
                        "saldo",
                        "mis-tarjetas"
                      ]
                    }
                  },
                  "response": []
                },
                {
                  "name": "Eliminar TarjetaCredito",
                  "request": {
                    "auth": {
                      "type": "bearer",
                      "bearer": [
                        {
                          "key": "token",
                          "value": "{{vault:authorization-secret}}",
                          "type": "string"
                        }
                      ]
                    },
                    "method": "DELETE",
                    "header": [],
                    "body": {
                      "mode": "raw",
                      "raw": "",
                      "options": {
                        "raw": {
                          "language": "json"
                        }
                      }
                    },
                    "url": {
                      "raw": "http://localhost:3005/api/v1/saldo/mis-tarjetas/69adbc3737825ef1391f949f",
                      "protocol": "http",
                      "host": [
                        "localhost"
                      ],
                      "port": "3005",
                      "path": [
                        "api",
                        "v1",
                        "saldo",
                        "mis-tarjetas",
                        "69adbc3737825ef1391f949f"
                      ]
                    }
                  },
                  "response": []
                },
                {
                  "name": "Verificar Tarjeta",
                  "request": {
                    "auth": {
                      "type": "bearer",
                      "bearer": [
                        {
                          "key": "token",
                          "value": "{{vault:authorization-secret}}",
                          "type": "string"
                        }
                      ]
                    },
                    "method": "POST",
                    "header": [],
                    "body": {
                      "mode": "raw",
                      "raw": "{\r\n  \"token\": \"701114\"\r\n}",
                      "options": {
                        "raw": {
                          "language": "json"
                        }
                      }
                    },
                    "url": {
                      "raw": "http://localhost:3005/api/v1/saldo/verificar-tarjeta",
                      "protocol": "http",
                      "host": [
                        "localhost"
                      ],
                      "port": "3005",
                      "path": [
                        "api",
                        "v1",
                        "saldo",
                        "verificar-tarjeta"
                      ]
                    }
                  },
                  "response": []
                }
              ]
            },
            {
              "name": "Recargas",
              "item": [
                {
                  "name": "Agregar Recarga",
                  "request": {
                    "auth": {
                      "type": "bearer",
                      "bearer": [
                        {
                          "key": "token",
                          "value": "{{vault:authorization-secret}}",
                          "type": "string"
                        }
                      ]
                    },
                    "method": "POST",
                    "header": [],
                    "body": {
                      "mode": "raw",
                      "raw": "{\r\n  \"tarjetaId\": \"69adbeb837825ef1391f94bd\",\r\n   \"monto\":     2000.00\r\n}",
                      "options": {
                        "raw": {
                          "language": "json"
                        }
                      }
                    },
                    "url": {
                      "raw": "http://localhost:3005/api/v1/saldo/recargar",
                      "protocol": "http",
                      "host": [
                        "localhost"
                      ],
                      "port": "3005",
                      "path": [
                        "api",
                        "v1",
                        "saldo",
                        "recargar"
                      ]
                    }
                  },
                  "response": []
                },
                {
                  "name": "Listar Recargas",
                  "protocolProfileBehavior": {
                    "disableBodyPruning": true
                  },
                  "request": {
                    "auth": {
                      "type": "bearer",
                      "bearer": [
                        {
                          "key": "token",
                          "value": "{{vault:authorization-secret}}",
                          "type": "string"
                        }
                      ]
                    },
                    "method": "GET",
                    "header": [],
                    "body": {
                      "mode": "raw",
                      "raw": "",
                      "options": {
                        "raw": {
                          "language": "json"
                        }
                      }
                    },
                    "url": {
                      "raw": "http://localhost:3005/api/v1/saldo/historial",
                      "protocol": "http",
                      "host": [
                        "localhost"
                      ],
                      "port": "3005",
                      "path": [
                        "api",
                        "v1",
                        "saldo",
                        "historial"
                      ]
                    }
                  },
                  "response": []
                },
                {
                  "name": "Ver saldo",
                  "protocolProfileBehavior": {
                    "disableBodyPruning": true
                  },
                  "request": {
                    "auth": {
                      "type": "bearer",
                      "bearer": [
                        {
                          "key": "token",
                          "value": "{{vault:authorization-secret}}",
                          "type": "string"
                        }
                      ]
                    },
                    "method": "GET",
                    "header": [],
                    "body": {
                      "mode": "raw",
                      "raw": "",
                      "options": {
                        "raw": {
                          "language": "json"
                        }
                      }
                    },
                    "url": {
                      "raw": "http://localhost:3005/api/v1/saldo/mi-saldo",
                      "protocol": "http",
                      "host": [
                        "localhost"
                      ],
                      "port": "3005",
                      "path": [
                        "api",
                        "v1",
                        "saldo",
                        "mi-saldo"
                      ]
                    }
                  },
                  "response": []
                }
              ]
            },
            {
              "name": "Ver mi Cuenta",
              "request": {
                "auth": {
                  "type": "bearer",
                  "bearer": [
                    {
                      "key": "token",
                      "value": "{{vault:authorization-secret}}",
                      "type": "string"
                    }
                  ]
                },
                "method": "GET",
                "header": [],
                "url": {
                  "raw": "http://localhost:3005/api/v1/cuenta/mi-cuenta",
                  "protocol": "http",
                  "host": [
                    "localhost"
                  ],
                  "port": "3005",
                  "path": [
                    "api",
                    "v1",
                    "cuenta",
                    "mi-cuenta"
                  ]
                }
              },
              "response": []
            },
            {
              "name": "Ver mis Multas",
              "request": {
                "auth": {
                  "type": "bearer",
                  "bearer": [
                    {
                      "key": "token",
                      "value": "{{vault:authorization-secret}}",
                      "type": "string"
                    }
                  ]
                },
                "method": "GET",
                "header": [],
                "url": {
                  "raw": "http://localhost:3005/api/v1/pagos/mis-multas",
                  "protocol": "http",
                  "host": [
                    "localhost"
                  ],
                  "port": "3005",
                  "path": [
                    "api",
                    "v1",
                    "pagos",
                    "mis-multas"
                  ]
                }
              },
              "response": []
            },
            {
              "name": "Pagar Multa",
              "request": {
                "auth": {
                  "type": "bearer",
                  "bearer": [
                    {
                      "key": "token",
                      "value": "{{vault:authorization-secret}}",
                      "type": "string"
                    }
                  ]
                },
                "method": "POST",
                "header": [],
                "body": {
                  "mode": "raw",
                  "raw": "{\r\n  \"multaId\":   \"69adc2bf37825ef1391f9506\",\r\n  \"tarjetaId\": \"69adc22637825ef1391f9500\"\r\n}",
                  "options": {
                    "raw": {
                      "language": "json"
                    }
                  }
                },
                "url": {
                  "raw": "http://localhost:3005/api/v1/pagos/pagar-multa",
                  "protocol": "http",
                  "host": [
                    "localhost"
                  ],
                  "port": "3005",
                  "path": [
                    "api",
                    "v1",
                    "pagos",
                    "pagar-multa"
                  ]
                }
              },
              "response": []
            },
            {
              "name": "Aumentar multa",
              "request": {
                "auth": {
                  "type": "bearer",
                  "bearer": [
                    {
                      "key": "token",
                      "value": "{{vault:authorization-secret}}",
                      "type": "string"
                    }
                  ]
                },
                "method": "PUT",
                "header": [],
                "url": {
                  "raw": "http://localhost:3005/api/v1/trafico/aumentar-multas",
                  "protocol": "http",
                  "host": [
                    "localhost"
                  ],
                  "port": "3005",
                  "path": [
                    "api",
                    "v1",
                    "trafico",
                    "aumentar-multas"
                  ]
                }
              },
              "response": []
            }
          ]
        },
        {
          "name": "Menu Admin",
          "item": [
            {
              "name": "Iniciar camara",
              "request": {
                "auth": {
                  "type": "bearer",
                  "bearer": [
                    {
                      "key": "token",
                      "value": "{{vault:authorization-secret}}",
                      "type": "string"
                    }
                  ]
                },
                "method": "POST",
                "header": [],
                "body": {
                  "mode": "raw",
                  "raw": "",
                  "options": {
                    "raw": {
                      "language": "json"
                    }
                  }
                },
                "url": {
                  "raw": "http://localhost:3005/api/v1/camara/iniciar",
                  "protocol": "http",
                  "host": [
                    "localhost"
                  ],
                  "port": "3005",
                  "path": [
                    "api",
                    "v1",
                    "camara",
                    "iniciar"
                  ]
                }
              },
              "response": []
            },
            {
              "name": "Agregar Datos del Automovil Copy",
              "request": {
                "method": "PUT",
                "header": [],
                "body": {
                  "mode": "raw",
                  "raw": "{\r\n    \"placa\": \"P-138KDN\",\r\n    \"modelo\": \"Chevrolet Spark\",\r\n    \"color\": \"Azul\",\r\n    \"anio\": \"2018\"\r\n}",
                  "options": {
                    "raw": {
                      "language": "json"
                    }
                  }
                },
                "url": {
                  "raw": "http://localhost:3005/api/v1/trafico/multas/69ad9cfcf39c3aae49802806",
                  "protocol": "http",
                  "host": [
                    "localhost"
                  ],
                  "port": "3005",
                  "path": [
                    "api",
                    "v1",
                    "trafico",
                    "multas",
                    "69ad9cfcf39c3aae49802806"
                  ]
                }
              },
              "response": []
            }
          ]
        },
        {
          "name": "Multa",
          "request": {
            "auth": {
              "type": "bearer",
              "bearer": [
                {
                  "key": "token",
                  "value": "{{vault:authorization-secret}}",
                  "type": "string"
                }
              ]
            },
            "method": "GET",
            "header": [],
            "url": {
              "raw": "http://localhost:3005/api/v1/trafico/multas",
              "protocol": "http",
              "host": [
                "localhost"
              ],
              "port": "3005",
              "path": [
                "api",
                "v1",
                "trafico",
                "multas"
              ]
            }
          },
          "response": []
        },
        {
          "name": "Ver multa por placa",
          "request": {
            "method": "GET",
            "header": [],
            "url": {
              "raw": ""
            }
          },
          "response": []
        }
      ]
    }
  ]
}